swh/__init__.py
swh/loader/__init__.py
swh/loader/dir/__init__.py
swh/loader/dir/converters.py
swh/loader/dir/loader.py
swh/loader/dir/py.typed
swh/loader/dir/tasks.py
swh/loader/dir/tests/__init__.py
swh/loader/dir/tests/test_converters.py
swh/loader/dir/tests/test_loader.py
swh/loader/dir/tests/resources/sample-folder.tgz
swh.loader.dir-0.0.35.dist-info/AUTHORS
swh.loader.dir-0.0.35.dist-info/LICENSE
swh.loader.dir-0.0.35.dist-info/METADATA
swh.loader.dir-0.0.35.dist-info/WHEEL
swh.loader.dir-0.0.35.dist-info/top_level.txt
swh.loader.dir-0.0.35.dist-info/RECORD
