Metadata-Version: 2.1
Name: swh.loader.dir
Version: 0.0.35
Summary: Software Heritage Directory Loader
Home-page: https://forge.softwareheritage.org/diffusion/DLDDIR
Author: Software Heritage developers
Author-email: swh-devel@inria.fr
License: UNKNOWN
Project-URL: Bug Reports, https://forge.softwareheritage.org/maniphest
Project-URL: Source, https://forge.softwareheritage.org/source/swh-loader-dir
Project-URL: Funding, https://www.softwareheritage.org/donate
Platform: UNKNOWN
Classifier: Programming Language :: Python :: 3
Classifier: Intended Audience :: Developers
Classifier: License :: OSI Approved :: GNU General Public License v3 (GPLv3)
Classifier: Operating System :: OS Independent
Classifier: Development Status :: 5 - Production/Stable
Requires-Dist: vcversioner
Requires-Dist: retrying
Requires-Dist: click
Requires-Dist: swh.model (>=0.0.27)
Requires-Dist: swh.scheduler (>=0.0.39)
Requires-Dist: swh.storage (>=0.0.83)
Requires-Dist: swh.loader.core (>=0.0.35)
Provides-Extra: testing
Requires-Dist: pytest ; extra == 'testing'
